{
  "fitness" : 0.6480862,
  "nodes" : [ {
    "id" : 4,
    "type" : "EnemyAndTreasure",
    "difficulty" : 0.8700657,
    "reward" : 0.9978697
  }, {
    "id" : 8,
    "type" : "Start",
    "difficulty" : 0.0,
    "reward" : 0.0
  }, {
    "id" : 10,
    "type" : "Treasure",
    "difficulty" : 0.0,
    "reward" : 0.9626349
  }, {
    "id" : 0,
    "type" : "EnemyAndTreasure",
    "difficulty" : 0.85288286,
    "reward" : 0.8532213
  }, {
    "id" : 13,
    "type" : "Treasure",
    "difficulty" : 0.0,
    "reward" : 0.9594214
  }, {
    "id" : 3,
    "type" : "EnemyAndTreasure",
    "difficulty" : 0.45856693,
    "reward" : 0.9729607
  }, {
    "id" : 6,
    "type" : "EnemyAndTreasure",
    "difficulty" : 0.8700657,
    "reward" : 0.9978697
  }, {
    "id" : 16,
    "type" : "Treasure",
    "difficulty" : 0.0,
    "reward" : 0.4571507
  }, {
    "id" : 12,
    "type" : "EnemyAndTreasure",
    "difficulty" : 0.24804597,
    "reward" : 0.9549523
  }, {
    "id" : 1,
    "type" : "Enemies",
    "difficulty" : 0.834363,
    "reward" : 0.0
  }, {
    "id" : 5,
    "type" : "EnemyAndTreasure",
    "difficulty" : 0.8700657,
    "reward" : 0.9978697
  }, {
    "id" : 14,
    "type" : "Treasure",
    "difficulty" : 0.0,
    "reward" : 0.72153664
  }, {
    "id" : 11,
    "type" : "Empty",
    "difficulty" : 0.0,
    "reward" : 0.0
  }, {
    "id" : 2,
    "type" : "Enemies",
    "difficulty" : 0.21111636,
    "reward" : 0.0
  }, {
    "id" : 7,
    "type" : "Treasure",
    "difficulty" : 0.0,
    "reward" : 0.9594214
  }, {
    "id" : 9,
    "type" : "Treasure",
    "difficulty" : 0.0,
    "reward" : 0.99626815
  }, {
    "id" : 17,
    "type" : "Exit",
    "difficulty" : 0.0,
    "reward" : 0.0
  }, {
    "id" : 15,
    "type" : "Empty",
    "difficulty" : 0.0,
    "reward" : 0.0
  }, {
    "id" : 18,
    "type" : "Enemies",
    "difficulty" : 0.41549763,
    "reward" : 0.0
  } ],
  "edges" : [ {
    "from" : 4,
    "to" : 7
  }, {
    "from" : 8,
    "to" : 12
  }, {
    "from" : 10,
    "to" : 14
  }, {
    "from" : 0,
    "to" : 1
  }, {
    "from" : 0,
    "to" : 2
  }, {
    "from" : 0,
    "to" : 3
  }, {
    "from" : 3,
    "to" : 6
  }, {
    "from" : 6,
    "to" : 9
  }, {
    "from" : 6,
    "to" : 10
  }, {
    "from" : 16,
    "to" : 18
  }, {
    "from" : 12,
    "to" : 16
  }, {
    "from" : 1,
    "to" : 4
  }, {
    "from" : 5,
    "to" : 8
  }, {
    "from" : 11,
    "to" : 15
  }, {
    "from" : 2,
    "to" : 5
  }, {
    "from" : 7,
    "to" : 11
  }, {
    "from" : 9,
    "to" : 13
  }, {
    "from" : 15,
    "to" : 17
  } ]
}